{
  "feed1": {
    "post": "To increase my vocabulary",
    "date": "Jan 23, 2020",
    "likes": 2,
    "isAnonymous": false,
    "goalId": "goal1",
    "uid": "12345"
  },
  "feed2": {
    "post": "I will work toward my goals for the sense of accomplishment that comes from productivity",
    "date": "Jan 23, 2020",
    "likes": 0,
    "isAnonymous": true,
    "goalId": "goal0",
    "uid": "54321"
  },
  "feed3": {
    "post": "I want to keep up with my kids",
    "date": "Jan 22, 2020",
    "likes": 1,
    "isAnonymous": false,
    "goalId": "goal4",
    "uid": "54321"
  },
  "feed4": {
    "post": "To pratice the skills I have learned in a cohesive project",
    "date": "Jan 22, 2020",
    "likes": 1,
    "isAnonymous": false,
    "goalId": "goal3",
    "uid": "12345"
  },
  "feed5": {
    "post": "Reading helps me relax and take my mind off stress",
    "date": "Jan 21, 2020",
    "likes": 0,
    "isAnonymous": false,
    "goalId": "goal1",
    "uid": "12345"
  },
  "feed6": {
    "post": "I want to fit into my clothes more comfortably without buying up a size",
    "date": "Jan 21, 2020",
    "likes": 1,
    "isAnonymous": false,
    "goalId": "goal4",
    "uid": "54321"
  },
  "feed7": {
    "post": "I want to take stress off my joints and feet",
    "date": "Jan 20, 2020",
    "likes": 0,
    "isAnonymous": false,
    "goalId": "goal4",
    "uid": "54321"
  },
  "feed8": {
    "post": "To learn about a variety of topics",
    "date": "Jan 20, 2020",
    "likes": 0,
    "isAnonymous": false,
    "goalId": "goal1",
    "uid": "12345"
  },
  "feed9": {
    "post": "Because running clears my head",
    "date": "Jan 20, 2020",
    "likes": 0,
    "isAnonymous": false,
    "goalId": "goal2",
    "uid": "01234"
  },
  "feed10": {
    "post": "Because litter in the carpet is gross!",
    "date": "Jan 20, 2020",
    "likes": 0,
    "isAnonymous": false,
    "goalId": "goal6",
    "uid": "09876"
  }
}